supvisors/__init__.py
supvisors/application.py
supvisors/commander.py
supvisors/context.py
supvisors/initializer.py
supvisors/instancestatus.py
supvisors/listener.py
supvisors/options.py
supvisors/plugin.py
supvisors/process.py
supvisors/rpcinterface.py
supvisors/rules.xsd
supvisors/sparser.py
supvisors/statemachine.py
supvisors/statscollector.py
supvisors/statscompiler.py
supvisors/strategy.py
supvisors/supervisordata.py
supvisors/supervisorupdater.py
supvisors/supvisorsctl.py
supvisors/ttypes.py
supvisors/utils.py
supvisors/version.txt
supvisors/client/__init__.py
supvisors/client/clientutils.py
supvisors/client/wssubscriber.py
supvisors/client/zmqsubscriber.py
supvisors/external_com/__init__.py
supvisors/external_com/eventinterface.py
supvisors/external_com/supvisorswebsocket.py
supvisors/external_com/supvisorszmq.py
supvisors/internal_com/__init__.py
supvisors/internal_com/internalinterface.py
supvisors/internal_com/mapper.py
supvisors/internal_com/multicast.py
supvisors/internal_com/rpchandler.py
supvisors/internal_com/supervisorproxy.py
supvisors/tests/__init__.py
supvisors/tests/base.py
supvisors/tests/configurations.py
supvisors/tests/conftest.py
supvisors/tests/test_application.py
supvisors/tests/test_breed.py
supvisors/tests/test_clientutils.py
supvisors/tests/test_commander.py
supvisors/tests/test_context.py
supvisors/tests/test_eventinterface.py
supvisors/tests/test_flask.py
supvisors/tests/test_initializer.py
supvisors/tests/test_instancestatus.py
supvisors/tests/test_internalinterface.py
supvisors/tests/test_listener.py
supvisors/tests/test_mapper.py
supvisors/tests/test_multicast.py
supvisors/tests/test_options.py
supvisors/tests/test_plot.py
supvisors/tests/test_plugin.py
supvisors/tests/test_process.py
supvisors/tests/test_rpchandler.py
supvisors/tests/test_rpcinterface.py
supvisors/tests/test_sparser.py
supvisors/tests/test_statemachine.py
supvisors/tests/test_statscollector.py
supvisors/tests/test_statscompiler.py
supvisors/tests/test_strategy.py
supvisors-0.18.7.dist-info/LICENSE
supvisors-0.18.7.dist-info/METADATA
supvisors-0.18.7.dist-info/WHEEL
supvisors-0.18.7.dist-info/entry_points.txt
supvisors-0.18.7.dist-info/top_level.txt
supvisors-0.18.7.dist-info/RECORD
