Metadata-Version: 2.1
Name: supvisors
Version: 0.18.7
Summary: A Control System for Distributed Applications
Home-page: https://github.com/julien6387/supvisors
Author: Julien Le Cléach
Author-email: julien.6387.dev@gmail.com
License: UNKNOWN
Download-URL: https://github.com/julien6387/supvisors/archive/0.18.7.tar.gz
Platform: Rocky 8.5
Classifier: License :: OSI Approved :: Apache Software License
Classifier: Development Status :: 5 - Production/Stable
Classifier: Intended Audience :: Developers
Classifier: Intended Audience :: System Administrators
Classifier: Natural Language :: English
Classifier: Environment :: No Input/Output (Daemon)
Classifier: Operating System :: POSIX :: Linux
Classifier: Programming Language :: Python :: 3.6
Classifier: Programming Language :: Python :: 3.7
Classifier: Programming Language :: Python :: 3.8
Classifier: Programming Language :: Python :: 3.9
Classifier: Programming Language :: Python :: 3.10
Classifier: Programming Language :: Python :: 3.11
Classifier: Programming Language :: Python :: 3.12
Classifier: Topic :: System :: Boot
Classifier: Topic :: System :: Monitoring
Classifier: Topic :: System :: Software Distribution
Requires-Python: >=3.6
License-File: LICENSE
Requires-Dist: supervisor (<4.3,>=4.2.4)
Provides-Extra: all
Requires-Dist: psutil (>=5.7.3) ; (python_version < "3.7") and extra == 'all'
Requires-Dist: pyparsing (<3,>=2.0.2) ; (python_version < "3.7") and extra == 'all'
Requires-Dist: matplotlib (>=3.3.3) ; (python_version < "3.7") and extra == 'all'
Requires-Dist: lxml (>=4.6.2) ; (python_version < "3.7") and extra == 'all'
Requires-Dist: flask-restx (==0.5.1) ; (python_version < "3.7") and extra == 'all'
Requires-Dist: Flask (<3) ; (python_version < "3.7") and extra == 'all'
Requires-Dist: Werkzeug (==2.0.3) ; (python_version < "3.7") and extra == 'all'
Requires-Dist: pyzmq (>=25.1.1) ; (python_version < "3.7") and extra == 'all'
Requires-Dist: psutil (>=5.7.3) ; (python_version >= "3.7") and extra == 'all'
Requires-Dist: pyparsing (<3,>=2.0.2) ; (python_version >= "3.7") and extra == 'all'
Requires-Dist: matplotlib (>=3.3.3) ; (python_version >= "3.7") and extra == 'all'
Requires-Dist: lxml (>=4.6.2) ; (python_version >= "3.7") and extra == 'all'
Requires-Dist: flask-restx (<1.3,>=1.1.0) ; (python_version >= "3.7") and extra == 'all'
Requires-Dist: pyzmq (>=25.1.1) ; (python_version >= "3.7") and extra == 'all'
Requires-Dist: websockets (<14,>=10.4) ; (python_version >= "3.7") and extra == 'all'
Provides-Extra: flask
Requires-Dist: flask-restx (==0.5.1) ; (python_version < "3.7") and extra == 'flask'
Requires-Dist: Flask (<3) ; (python_version < "3.7") and extra == 'flask'
Requires-Dist: Werkzeug (==2.0.3) ; (python_version < "3.7") and extra == 'flask'
Requires-Dist: flask-restx (<1.3,>=1.1.0) ; (python_version >= "3.7") and extra == 'flask'
Provides-Extra: statistics
Requires-Dist: psutil (>=5.7.3) ; extra == 'statistics'
Requires-Dist: pyparsing (<3,>=2.0.2) ; extra == 'statistics'
Requires-Dist: matplotlib (>=3.3.3) ; extra == 'statistics'
Provides-Extra: testing
Requires-Dist: pytest (>=2.5.2) ; extra == 'testing'
Requires-Dist: pytest-cov ; extra == 'testing'
Requires-Dist: pytest-mock ; extra == 'testing'
Requires-Dist: pytest-asyncio (<0.22) ; extra == 'testing'
Provides-Extra: ws
Requires-Dist: websockets (<14,>=10.4) ; (python_version >= "3.7") and extra == 'ws'
Provides-Extra: xml_valid
Requires-Dist: lxml (>=4.6.2) ; extra == 'xml_valid'
Provides-Extra: zmq
Requires-Dist: pyzmq (>=25.1.1) ; extra == 'zmq'
